pragmatic_business_rules/__init__.py
pragmatic_business_rules/action.py
pragmatic_business_rules/asserts.py
pragmatic_business_rules/condition.py
pragmatic_business_rules/main.py
pragmatic_business_rules/types.py
pragmatic_business_rules/validators.py
pragmatic_business_rules-0.5.0.dist-info/METADATA
pragmatic_business_rules-0.5.0.dist-info/WHEEL
pragmatic_business_rules-0.5.0.dist-info/licenses/LICENSE
pragmatic_business_rules-0.5.0.dist-info/RECORD
